AUTHORS
LICENSE
MANIFEST.in
setup.py
MarkWiki.egg-info/PKG-INFO
MarkWiki.egg-info/SOURCES.txt
MarkWiki.egg-info/dependency_links.txt
MarkWiki.egg-info/entry_points.txt
MarkWiki.egg-info/not-zip-safe
MarkWiki.egg-info/requires.txt
MarkWiki.egg-info/top_level.txt
docs/releases.rst
markwiki/__init__.py
markwiki/application.py
markwiki/config.py
markwiki/exceptions.py
markwiki/forms.py
markwiki/freezer.py
markwiki/renderer.py
markwiki/server.py
markwiki/util.py
markwiki/validators.py
markwiki/wiki.py
markwiki/wikilinks.py
markwiki/authn/__init__.py
markwiki/authn/manager.py
markwiki/git/__init__.py
markwiki/git/git_integration.py
markwiki/models/__init__.py
markwiki/models/user.py
markwiki/search/__init__.py
markwiki/search/engine.py
markwiki/search/schema.py
markwiki/static/jquery-2.0.0.min.js
markwiki/static/persona.js
markwiki/static/persona.png
markwiki/static/pygments-pastie.css
markwiki/static/bs/css/bootstrap-theme.min.3.3.4.css
markwiki/static/bs/css/bootstrap.min.3.3.4.css
markwiki/static/bs/fonts/glyphicons-halflings-regular.eot
markwiki/static/bs/fonts/glyphicons-halflings-regular.svg
markwiki/static/bs/fonts/glyphicons-halflings-regular.ttf
markwiki/static/bs/fonts/glyphicons-halflings-regular.woff
markwiki/static/bs/fonts/glyphicons-halflings-regular.woff2
markwiki/static/bs/js/bootstrap.min.3.3.4.js
markwiki/storage/__init__.py
markwiki/storage/factory.py
markwiki/storage/user.py
markwiki/storage/fs/__init__.py
markwiki/storage/fs/user.py
markwiki/templates/add_user.html
markwiki/templates/administrate.html
markwiki/templates/base.html
markwiki/templates/create.html
markwiki/templates/edit.html
markwiki/templates/history.html
markwiki/templates/internal_server_error.html
markwiki/templates/list.html
markwiki/templates/login.html
markwiki/templates/method_not_allowed.html
markwiki/templates/register.html
markwiki/templates/search.html
markwiki/templates/user_confirmation.html
markwiki/templates/view_history.html
markwiki/templates/wiki.html
markwiki/templates/MarkWiki/Deployment.md
markwiki/templates/MarkWiki/FAQ.md
markwiki/templates/MarkWiki/Features.md
markwiki/templates/MarkWiki/Help.md
markwiki/templates/MarkWiki/Introduction.md
markwiki/templates/MarkWiki/Settings.md
